nhl_predictor/__init__.py
nhl_predictor/main.py
nhl_predictor/builder/__init__.py
nhl_predictor/builder/builder.py
nhl_predictor/model/__init__.py
nhl_predictor/model/algorithms.py
nhl_predictor/model/game_state.py
nhl_predictor/model/game_type.py
nhl_predictor/model/home_or_away.py
nhl_predictor/model/position.py
nhl_predictor/model/seasons.py
nhl_predictor/model/summarizer_manager.py
nhl_predictor/model/team_map.py
nhl_predictor/model/summarizers/__init__.py
nhl_predictor/model/summarizers/average_player_summarizer.py
nhl_predictor/model/summarizers/summarizer.py
nhl_predictor/predictor/__init__.py
nhl_predictor/predictor/linear_regression.py
nhl_predictor/predictor/predictor.py
nhl_predictor/predictor/tensor_test.py
nhl_predictor/shared/__init__.py
nhl_predictor/shared/config.jog.yaml
nhl_predictor/shared/execution_context.py
nhl_predictor/shared/logging_config.py
nhl_predictor/shared/utility.py
nhl_predictor/shared/constants/__init__.py
nhl_predictor/shared/constants/database.py
nhl_predictor/shared/constants/json.py
nhl_predictor/trainer/__init__.py
nhl_predictor/trainer/linear_regression.py
nhl_predictor/trainer/trainer.py
nhl_predictor-0.3.6.dist-info/METADATA
nhl_predictor-0.3.6.dist-info/WHEEL
nhl_predictor-0.3.6.dist-info/entry_points.txt
nhl_predictor-0.3.6.dist-info/licenses/LICENSE
nhl_predictor-0.3.6.dist-info/RECORD
