Metadata-Version: 2.4
Name: NHL-predictor
Version: 0.3.6
Summary: Tool to use NHL API stats to predict future game outcomes.
Project-URL: Homepage, https://github.com/MattRWallace/NHLPredictor/
Project-URL: Issues, https://github.com/MattRWallace/NHLPredictor/issues
Author-email: Matthew Wallace <matthew.r.wallace@live.com>
License-Expression: GPL-3.0-or-later
License-File: LICENSE
Classifier: Development Status :: 4 - Beta
Classifier: Environment :: Console
Classifier: Intended Audience :: Developers
Classifier: Intended Audience :: End Users/Desktop
Classifier: License :: OSI Approved :: GNU General Public License v3 or later (GPLv3+)
Classifier: Operating System :: OS Independent
Classifier: Programming Language :: Python :: 3
Classifier: Topic :: Scientific/Engineering :: Information Analysis
Requires-Python: >=3.0
Requires-Dist: ansimarkup==2.1.0
Requires-Dist: daterangeparser==1.3.2
Requires-Dist: nhl-api-py==3.0.2
Requires-Dist: numpy==2.4.0
Requires-Dist: pandas==2.3.3
Requires-Dist: python-dateutil==2.9.0.post0
Requires-Dist: python-json-logger==4.0.0
Requires-Dist: requests==2.32.5
Requires-Dist: scikit-learn==1.8.0
Requires-Dist: sqlitedict==2.1.0
Requires-Dist: statsmodels==0.14.5
Requires-Dist: tensorflow-cpu==2.20.0
Requires-Dist: typer==0.20.1
Requires-Dist: typing-extensions==4.15.0
